spot_optimizer/__init__.py
spot_optimizer/cli.py
spot_optimizer/config.py
spot_optimizer/optimizer_mode.py
spot_optimizer/query_builder.py
spot_optimizer/resources/instance_metadata.json
spot_optimizer/spot_advisor_data/__init__.py
spot_optimizer/spot_advisor_data/aws_spot_advisor_cache.py
spot_optimizer/spot_advisor_engine.py
spot_optimizer/spot_optimizer.py
spot_optimizer/storage_engine/__init__.py
spot_optimizer/storage_engine/duckdb_storage_engine.py
spot_optimizer/storage_engine/storage_engine.py
spot_optimizer/validators.py
spot_optimizer-1.2.9.dist-info/METADATA
spot_optimizer-1.2.9.dist-info/WHEEL
spot_optimizer-1.2.9.dist-info/entry_points.txt
spot_optimizer-1.2.9.dist-info/licenses/LICENSE
spot_optimizer-1.2.9.dist-info/RECORD
