Metadata-Version: 2.4
Name: spot-optimizer
Version: 1.2.9
Summary: AWS EC2 spot instance optimizer
License-File: LICENSE
Keywords: aws,ec2,spot,optimizer
Author: Amar Prakash
Author-email: amar.om1994@gmail.com
Requires-Python: >=3.9
Classifier: Programming Language :: Python :: 3
Classifier: Programming Language :: Python :: 3.9
Classifier: Programming Language :: Python :: 3.10
Classifier: Programming Language :: Python :: 3.11
Classifier: Programming Language :: Python :: 3.12
Classifier: Programming Language :: Python :: 3.13
Classifier: Programming Language :: Python :: 3.14
Requires-Dist: appdirs (>=1.4.4,<2.0.0)
Requires-Dist: boto3 (>=1.34.0,<2.0.0)
Requires-Dist: diskcache (>=5.6.3,<6.0.0)
Requires-Dist: duckdb (>=1.1.3,<2.0.0)
Requires-Dist: pandas (>=2.2.0,<3.0.0)
Requires-Dist: requests (>=2.32.3,<3.0.0)
Requires-Dist: tqdm (>=4.66.1,<5.0.0)
Requires-Dist: urllib3 (<2.0.0)
Project-URL: Repository, https://github.com/amarlearning/spot-optimizer
